IPregexo/IPregexo.py
IPregexo/__init__.py
IPregexo-0.0.2.dist-info/LICENSE
IPregexo-0.0.2.dist-info/METADATA
IPregexo-0.0.2.dist-info/WHEEL
IPregexo-0.0.2.dist-info/top_level.txt
IPregexo-0.0.2.dist-info/RECORD
