Metadata-Version: 2.1
Name: IPregexo
Version: 0.0.2
Summary: Validating and classifying IPv4 address
Home-page: https://github.com/omarthe95/IPregexo
Author: Omar Adil
Author-email: xomaradilxa@gmail.com
License: UNKNOWN
Platform: UNKNOWN
Classifier: Programming Language :: Python :: 3
Classifier: License :: OSI Approved :: MIT License
Classifier: Operating System :: OS Independent
Requires-Python: >=3.5
